main.py
setup.py
algorithm/__init__.py
algorithm/generate.py
algorithm/map.py
algorithm/search.py
magic_maze-2.0.6.data/data/LICENSE
magic_maze-2.0.6.data/data/README.md
magic_maze-2.0.6.data/data/demo/15X20.map
magic_maze-2.0.6.data/data/doc/algorithm.txt
magic_maze-2.0.6.data/data/doc/demo-2d.png
magic_maze-2.0.6.data/data/doc/demo-3d.png
magic_maze-2.0.6.data/data/doc/owner.jpg
magic_maze-2.0.6.data/data/script/generate_doc.sh
magic_maze-2.0.6.data/data/script/test.sh
magic_maze-2.0.6.data/data/script/upload.sh
magic_maze-2.0.6.data/data/ui/panda3d/models/ball.egg.pz
magic_maze-2.0.6.data/data/ui/panda3d/models/bamboo_leaves.jpg
magic_maze-2.0.6.data/data/ui/panda3d/models/iron05.jpg
magic_maze-2.0.6.data/data/ui/panda3d/models/limba.jpg
magic_maze-2.0.6.data/data/ui/panda3d/models/maze.png
magic_maze-2.0.6.data/data/ui/pyqt/resources/flag.png
magic_maze-2.0.6.data/data/ui/pyqt/resources/maze.ico
magic_maze-2.0.6.data/data/ui/pyqt/resources/maze.png
magic_maze-2.0.6.data/data/ui/pyqt/resources/run.png
ui/__init__.py
ui/qt_main.py
ui/panda3d/__init__.py
ui/panda3d/main.py
ui/panda3d/models/ball.egg.pz
ui/panda3d/models/bamboo_leaves.jpg
ui/panda3d/models/iron05.jpg
ui/panda3d/models/limba.jpg
ui/panda3d/models/maze.png
ui/pyqt/__init__.py
ui/pyqt/main.py
ui/pyqt/resources/flag.png
ui/pyqt/resources/maze.ico
ui/pyqt/resources/maze.png
ui/pyqt/resources/run.png
magic_maze-2.0.6.dist-info/LICENSE
magic_maze-2.0.6.dist-info/METADATA
magic_maze-2.0.6.dist-info/WHEEL
magic_maze-2.0.6.dist-info/entry_points.txt
magic_maze-2.0.6.dist-info/top_level.txt
magic_maze-2.0.6.dist-info/RECORD
