Metadata-Version: 2.1
Name: magic-maze
Version: 2.0.6
Summary: maze game developed by python
Home-page: https://github.com/HeLiangHIT/magic_maze
Author: He Liang
Author-email: heianghit@foxmail.com
License: Mulan PSL v2
Keywords: maze pyqt
Platform: UNKNOWN
Classifier: Programming Language :: Python :: 3
Classifier: Development Status :: 5 - Production/Stable
Classifier: Natural Language :: Chinese (Simplified)
Classifier: Environment :: Console
Classifier: Intended Audience :: Developers
Classifier: Intended Audience :: End Users/Desktop
Classifier: Operating System :: OS Independent
Classifier: Topic :: Games/Entertainment
Classifier: License :: OSI Approved :: Mulan Permissive Software License v2 (MulanPSL-2.0)
License-File: LICENSE
Requires-Dist: Panda3D (>=1.10.13)
Requires-Dist: PyQt5 (>=5.15.4)
Requires-Dist: fire (>=0.5.0)
